relace_agent_client/__init__.py
relace_agent_client/api/__init__.py
relace_agent_client/api/default/__init__.py
relace_agent_client/api/default/ask_question.py
relace_agent_client/api/default/clone_repo.py
relace_agent_client/api/default/create_repo.py
relace_agent_client/api/default/delete_file.py
relace_agent_client/api/default/delete_repo.py
relace_agent_client/api/default/download_file.py
relace_agent_client/api/default/get_repo_metadata.py
relace_agent_client/api/default/list_repo_metadata.py
relace_agent_client/api/default/retrieve_relevant_content.py
relace_agent_client/api/default/update_repo_contents.py
relace_agent_client/api/default/upload_file.py
relace_agent_client/client.py
relace_agent_client/errors.py
relace_agent_client/models/__init__.py
relace_agent_client/models/file.py
relace_agent_client/models/file_delete_operation.py
relace_agent_client/models/file_rename_operation.py
relace_agent_client/models/file_write_operation.py
relace_agent_client/models/http_validation_error.py
relace_agent_client/models/list_repo_metadata_order_by.py
relace_agent_client/models/paged_response_repo_metadata.py
relace_agent_client/models/repo_ask_request.py
relace_agent_client/models/repo_ask_response.py
relace_agent_client/models/repo_clone_response.py
relace_agent_client/models/repo_cloned_file.py
relace_agent_client/models/repo_create_files_source.py
relace_agent_client/models/repo_create_git_source.py
relace_agent_client/models/repo_create_legacy_request.py
relace_agent_client/models/repo_create_legacy_request_metadata_type_0.py
relace_agent_client/models/repo_create_relace_source.py
relace_agent_client/models/repo_create_request.py
relace_agent_client/models/repo_create_request_metadata_type_0.py
relace_agent_client/models/repo_info.py
relace_agent_client/models/repo_metadata.py
relace_agent_client/models/repo_metadata_metadata_type_0.py
relace_agent_client/models/repo_retrieve_request.py
relace_agent_client/models/repo_retrieve_response.py
relace_agent_client-0.2.0.dist-info/WHEEL
relace_agent_client-0.2.0.dist-info/METADATA
relace_agent_client-0.2.0.dist-info/RECORD
