Metadata-Version: 2.3
Name: relace-agent-client
Version: 0.2.0
Summary: A client library for accessing Relace Agent
Requires-Dist: httpx>=0.23.0,<0.29.0
Requires-Dist: attrs>=22.2.0
Requires-Dist: python-dateutil>=2.8.0,<3
Requires-Python: ~=3.9
Project-URL: Homepage, https://docs.relace.ai
Project-URL: Issues, https://github.com/squack-io/relace-sdk/issues
